lisainstrument/__init__.py
lisainstrument/__main__.py
lisainstrument/cli/__init__.py
lisainstrument/cli/run_simulation.py
lisainstrument/freqplan/__init__.py
lisainstrument/freqplan/fplan_file.py
lisainstrument/freqplan/fplan_source.py
lisainstrument/freqplan/fplan_source_interp.py
lisainstrument/glitches/__init__.py
lisainstrument/glitches/glitch_file.py
lisainstrument/glitches/glitch_source.py
lisainstrument/glitches/glitch_source_interp.py
lisainstrument/gwsource/__init__.py
lisainstrument/gwsource/gw_file.py
lisainstrument/gwsource/gw_source.py
lisainstrument/gwsource/hdf5util.py
lisainstrument/instru/__init__.py
lisainstrument/instru/instru_defaults.py
lisainstrument/instru/instru_file_reader.py
lisainstrument/instru/instru_file_reader_v2_0_0.py
lisainstrument/instru/instru_filter.py
lisainstrument/instru/instru_formulas.py
lisainstrument/instru/instru_fplan.py
lisainstrument/instru/instru_glitchsrc.py
lisainstrument/instru/instru_gwsrc.py
lisainstrument/instru/instru_locking.py
lisainstrument/instru/instru_model.py
lisainstrument/instru/instru_noises.py
lisainstrument/instru/instru_orbsrc.py
lisainstrument/instru/instru_store.py
lisainstrument/instru/instru_store_v2_0_0.py
lisainstrument/instrument.py
lisainstrument/legacy/__init__.py
lisainstrument/legacy/containers.py
lisainstrument/legacy/dsp.py
lisainstrument/legacy/dynamic_delay_dsp.py
lisainstrument/legacy/fixed_shift_dsp.py
lisainstrument/legacy/hexagon.py
lisainstrument/legacy/legacy_plots.py
lisainstrument/legacy/noises.py
lisainstrument/legacy/pyplnoise/LICENSE
lisainstrument/legacy/pyplnoise/__init__.py
lisainstrument/legacy/pyplnoise/pyplnoise.py
lisainstrument/noisy/__init__.py
lisainstrument/noisy/estimate_psd.py
lisainstrument/noisy/noise_defs.py
lisainstrument/noisy/noise_defs_lisa.py
lisainstrument/noisy/noise_gen_numpy.py
lisainstrument/orbiting/__init__.py
lisainstrument/orbiting/constellation_enums.py
lisainstrument/orbiting/orbit_file.py
lisainstrument/orbiting/orbit_source.py
lisainstrument-2.1.0.dist-info/LICENSE
lisainstrument-2.1.0.dist-info/METADATA
lisainstrument-2.1.0.dist-info/WHEEL
lisainstrument-2.1.0.dist-info/entry_points.txt
lisainstrument-2.1.0.dist-info/RECORD
