Metadata-Version: 2.3
Name: lisainstrument
Version: 2.1.0
Summary: Simulates the LISA measurement chain (noise and signals) and generates telemetry data
Home-page: https://gitlab.in2p3.fr/lisa-simulation/instrument
License: BSD 3-Clause
Author: Jean-Baptiste Bayle
Author-email: j2b.bayle@gmail.com
Maintainer: Jean-Baptiste Bayle
Maintainer-email: j2b.bayle@gmail.com
Requires-Python: >=3.10,<4.0
Classifier: Intended Audience :: Science/Research
Classifier: License :: Other/Proprietary License
Classifier: Programming Language :: Python :: 3
Classifier: Programming Language :: Python :: 3.10
Classifier: Programming Language :: Python :: 3.11
Classifier: Programming Language :: Python :: 3.12
Classifier: Programming Language :: Python :: 3.13
Classifier: Topic :: Scientific/Engineering :: Astronomy
Classifier: Topic :: Scientific/Engineering :: Physics
Requires-Dist: attrs (>=25.3.0,<26.0.0)
Requires-Dist: bokeh (>=3.6.2,<4.0.0)
Requires-Dist: dask (==2025.3.0)
Requires-Dist: graphviz (>=0.20.3,<0.21.0)
Requires-Dist: h5py (>=3.12.1,<4.0.0)
Requires-Dist: lisaconstants (>=2.0.1,<3.0.0)
Requires-Dist: matplotlib (>=3.9.2,<4.0.0)
Requires-Dist: numpy (>=2.1.2,<3.0.0)
Requires-Dist: pyyaml (>=6.0.2,<7.0.0)
Requires-Dist: scipy (>=1.14.1,<2.0.0)
Requires-Dist: typing-extensions (>=4.15.0,<5.0.0)
Project-URL: Documentation, https://lisa-simulation.pages.in2p3.fr/instrument
Project-URL: Download, https://gitlab.in2p3.fr/lisa-simulation/instrument/-/releases
Project-URL: Repository, https://gitlab.in2p3.fr/lisa-simulation/instrument
Project-URL: Tracker, https://gitlab.in2p3.fr/lisa-simulation/instrument/-/issues
